{
    "data": {
        "solutionArticle": {
            "ipRegion": "未知归属地",
            "rewardEnabled": null,
            "canEditReward": false,
            "uuid": "hBKVyZ",
            "title": "期望个数统计 期望计算与证明",
            "content": "## 题意概述：\n\n对于一个排好序的序列，对相同的数字随机打乱顺序后期望有多少个数字保持原位置不变。\n\n## 题解\n经过分析，我们发现不同能力值的简历是不会互相影响的，所以问题可以简化为有一个长度为 $n$ 的的数组，将里面的元素按照全排列随机排序后，问有多少个元素还在原位。设这个随机变量为 $X$ ，并且设 $X_i$ 是第 $i$ 个元素还在原位的 0-1 变量，即如果第 $i$ 个元素还在原位， $X_i = 1$ ，否则 $X_i = 0$。每一个元素随机排序后还在原位的概率是 $\\frac{1}{n}$ 。\n\n由期望的可加性，我们可以得到 \n\n$$E(X) = E(X_0 + X_1 + \\cdots + X_{n - 1}) = \\sum_{0 \\leq i < n}E(X_i) = \\frac{1}{n} * n = 1$$\n\n我们发现$E(X)$跟数组元素的长度**无关**，所以我们只需要求这个数组中的不同数字的个数即可。\n\n### 方法一：\n\n排序 + 除重\n\n```C++\nclass Solution {\npublic:\n    int expectNumber(vector<int>& scores) {\n        sort(scores.begin(), scores.end());\n        return unique(scores.begin(), scores.end()) - scores.begin();\n    }\n};\n```\n\n#### 复杂度分析\n\n* 时间复杂度：$O(N \\log N)$，其中 $N$ 是数组的大小。\n\n* 空间复杂度：$O(N)$。\n\n### 方法二：\n\n哈希表\n```Python\nclass Solution:\n    def expectNumber(self, scores: List[int]) -> int:\n        return len(set(scores))\n```\n\n#### 复杂度分析\n\n* 时间复杂度：$O(N)$，其中 $N$ 是数组的大小。\n\n* 空间复杂度：$O(N)$。",
            "slateValue": "",
            "slug": "qi-wang-ge-shu-tong-ji-qi-wang-ji-suan-yu-zheng-mi",
            "sunk": false,
            "chargeType": "FREE",
            "status": "PUBLISHED",
            "identifier": "hBKVyZ",
            "canEdit": false,
            "canSee": true,
            "reactionType": null,
            "reactionsV2": [
                {
                    "count": 10,
                    "reactionType": "UPVOTE"
                },
                {
                    "count": 1,
                    "reactionType": "AWESOME"
                }
            ],
            "tags": [
                {
                    "name": "Math",
                    "nameTranslated": "数学",
                    "slug": "math",
                    "tagType": "TOPIC"
                },
                {
                    "name": "C++",
                    "nameTranslated": "",
                    "slug": "cpp",
                    "tagType": "LANGUAGE"
                },
                {
                    "name": "Python",
                    "nameTranslated": "",
                    "slug": "python",
                    "tagType": "LANGUAGE"
                }
            ],
            "createdAt": "2020-04-29T05:46:34.161031+00:00",
            "thumbnail": "",
            "author": {
                "username": "LeetCode-Solution",
                "certificationLevel": "OFFICIAL",
                "isDiscussAdmin": true,
                "isDiscussStaff": true,
                "profile": {
                    "userAvatar": "https://assets.leetcode.cn/aliyun-lc-upload/users/leetcode-solution/avatar_1582018938.png",
                    "userSlug": "leetcode-solution",
                    "realName": "力扣官方题解",
                    "reputation": 245
                }
            },
            "summary": "题意概述： 对于一个排好序的序列，对相同的数字随机打乱顺序后期望有多少个数字保持原位置不变。 题解 经过分析，我们发现不同能力值的简历是不会互相影响的，所以问题可以简化为有一个长度为 $n$ 的的数组，将里面的元素按照全排列随机排序后，问有多少个元素还在原位。设这个随机变量为 $X$ ，并且设 $X_i$ 是第 $i$",
            "topic": {
                "id": 224888,
                "subscribed": false,
                "commentCount": 19,
                "viewCount": 6713,
                "post": {
                    "id": 598013,
                    "status": "Open",
                    "voteStatus": 0,
                    "isOwnPost": false
                }
            },
            "byLeetcode": true,
            "isMyFavorite": false,
            "isMostPopular": false,
            "favoriteCount": 20,
            "isEditorsPick": false,
            "hitCount": 10709,
            "videosInfo": [],
            "question": {
                "titleSlug": "qi-wang-ge-shu-tong-ji",
                "questionFrontendId": "LCP 11"
            },
            "next": {
                "slug": "ji-suan-bu-tong-shu-de-ge-shu-ji-ke-zhong-dian-shi",
                "title": "计算不同数的个数即可（重点是证明过程）"
            },
            "prev": null
        }
    }
}