{
    "data": {
        "question": {
            "questionId": "2907",
            "questionFrontendId": "2804",
            "categoryTitle": "JavaScript",
            "boundTopicId": 2371139,
            "title": "Array Prototype ForEach",
            "titleSlug": "array-prototype-foreach",
            "content": null,
            "translatedTitle": "数组原型的 forEach 方法",
            "translatedContent": null,
            "isPaidOnly": true,
            "difficulty": "Easy",
            "likes": 0,
            "dislikes": 0,
            "isLiked": null,
            "similarQuestions": "[]",
            "contributors": [],
            "langToValidPlayground": null,
            "topicTags": [],
            "companyTagStats": null,
            "codeSnippets": null,
            "stats": "{\"totalAccepted\": \"38\", \"totalSubmission\": \"45\", \"totalAcceptedRaw\": 38, \"totalSubmissionRaw\": 45, \"acRate\": \"84.4%\"}",
            "hints": [],
            "solution": null,
            "status": null,
            "sampleTestCase": "[1,2,3]\nfunction(val, i, arr){ arr[i] = val * 2 }\n{\"context\": true}",
            "metaData": "{\n  \"name\": \"foobar\",\n  \"params\": [\n    {\n      \"name\": \"arr\",\n      \"type\": \"string\"\n    },\n    {\n      \"type\": \"string\",\n      \"name\": \"callback\"\n    },\n    {\n      \"type\": \"string\",\n      \"name\": \"context\"\n    }\n  ],\n  \"return\": {\n    \"type\": \"integer\"\n  },\n  \"languages\": [\n    \"javascript\",\n    \"typescript\"\n  ],\n  \"manual\": true\n}",
            "judgerAvailable": true,
            "judgeType": "large",
            "mysqlSchemas": [],
            "enableRunCode": true,
            "envInfo": "{\"javascript\":[\"JavaScript\",\"<p>\\u7248\\u672c\\uff1a<code>Node.js 16.13.2<\\/code><\\/p>\\r\\n\\r\\n<p>\\u60a8\\u7684\\u4ee3\\u7801\\u5728\\u6267\\u884c\\u65f6\\u5c06\\u5e26\\u4e0a <code>--harmony<\\/code> \\u6807\\u8bb0\\u6765\\u5f00\\u542f <a href=\\\"http:\\/\\/node.green\\/\\\" target=\\\"_blank\\\">\\u65b0\\u7248ES6\\u7279\\u6027<\\/a>\\u3002<\\/p>\\r\\n\\r\\n<p><a href=\\\"https:\\/\\/lodash.com\\\" target=\\\"_blank\\\">lodash.js<\\/a> \\u5e93\\u5df2\\u7ecf\\u9ed8\\u8ba4\\u88ab\\u5305\\u542b\\u3002<\\/p>\\r\\n\\r\\n<p> \\u5982\\u9700\\u4f7f\\u7528\\u961f\\u5217\\/\\u4f18\\u5148\\u961f\\u5217\\uff0c\\u60a8\\u53ef\\u4f7f\\u7528 <a href=\\\"https:\\/\\/github.com\\/datastructures-js\\/priority-queue\\/tree\\/fb4fdb984834421279aeb081df7af624d17c2a03\\\" target=\\\"_blank\\\"> datastructures-js\\/priority-queue@5.3.0<\\/a> \\u548c <a href=\\\"https:\\/\\/github.com\\/datastructures-js\\/queue\\/tree\\/e63563025a5a805aa16928cb53bcd517bfea9230\\\" target=\\\"_blank\\\"> datastructures-js\\/queue@4.2.1<\\/a>\\u3002<\\/p>\"],\"typescript\":[\"TypeScript\",\"<p>TypeScript 5.1.6<\\/p>\\r\\n\\r\\n<p>Compile Options: --alwaysStrict --strictBindCallApply --strictFunctionTypes --target ES2022<\\/p>\\r\\n\\r\\n<p><a href=\\\"https:\\/\\/lodash.com\\\" target=\\\"_blank\\\">lodash.js<\\/a> \\u5e93\\u5df2\\u7ecf\\u9ed8\\u8ba4\\u88ab\\u5305\\u542b\\u3002<\\/p>\\r\\n\\r\\n<p> \\u5982\\u9700\\u4f7f\\u7528\\u961f\\u5217\\/\\u4f18\\u5148\\u961f\\u5217\\uff0c\\u60a8\\u53ef\\u4f7f\\u7528 <a href=\\\"https:\\/\\/github.com\\/datastructures-js\\/priority-queue\\/tree\\/fb4fdb984834421279aeb081df7af624d17c2a03\\\" target=\\\"_blank\\\"> datastructures-js\\/priority-queue@5.3.0<\\/a> \\u548c <a href=\\\"https:\\/\\/github.com\\/datastructures-js\\/queue\\/tree\\/e63563025a5a805aa16928cb53bcd517bfea9230\\\" target=\\\"_blank\\\"> datastructures-js\\/queue@4.2.1<\\/a>\\u3002<\\/p>\"]}",
            "book": null,
            "isSubscribed": false,
            "isDailyQuestion": false,
            "dailyRecordStatus": null,
            "editorType": "CKEDITOR",
            "ugcQuestionId": null,
            "style": "LEETCODE",
            "exampleTestcases": "[1,2,3]\nfunction(val, i, arr){ arr[i] = val * 2 }\n{\"context\": true}\n[true, true, false, false]\nfunction(val, i, arr){ arr[i] = this }\n{\"context\": false}\n[true, true, false, false]\nfunction(val, i, arr){ arr[i] = !val }\n{\"context\": 5}",
            "__typename": "QuestionNode"
        }
    }
}