{
    "data": {
        "solutionArticle": {
            "ipRegion": "未知归属地",
            "rewardEnabled": null,
            "canEditReward": false,
            "uuid": "pCQxEs",
            "title": "删除每行中的最大值",
            "content": "#### 方法一：排序\n\n**思路与算法**\n\n我们将题目给出大小为 $m \\times n$ 的矩阵 $\\textit{grid}$ 每一行从小到大排序，那么题目等价于每次删除矩阵的末尾列，得分为该列的最大值。那么最后的答案就是每一列的最大值之和。\n\n**代码**\n\n```Python [sol1-Python3]\nclass Solution:\n    def deleteGreatestValue(self, grid: List[List[int]]) -> int:\n        for i in grid:\n            i.sort()\n        return sum([max(i) for i in zip(*grid)])\n```\n\n```Java [sol1-Java]\nclass Solution {\n    public int deleteGreatestValue(int[][] grid) {\n        int m = grid.length, n = grid[0].length;\n        for (int i = 0; i < m; i++) {\n            Arrays.sort(grid[i]);\n        }\n        int res = 0;\n        for (int j = 0; j < n; j++) {\n            int mx = 0;\n            for (int i = 0; i < m; i++) {\n                mx = Math.max(mx, grid[i][j]);\n            }\n            res += mx;\n        }\n        return res;\n    }\n}\n```\n\n```C++ [sol1-C++]\nclass Solution {\npublic:\n    int deleteGreatestValue(vector<vector<int>>& grid) {\n        int m = grid.size(), n = grid[0].size();\n        for (int i = 0; i < m; i++) {\n            sort(grid[i].begin(), grid[i].end());\n        }\n        int res = 0;\n        for (int j = 0; j < n; j++) {\n            int mx = 0;\n            for (int i = 0; i < m; i++) {\n                mx = max(mx, grid[i][j]);\n            }\n            res += mx;\n        }\n        return res;\n    }\n};\n```\n\n```C# [sol1-C#]\npublic class Solution {\n    public int DeleteGreatestValue(int[][] grid) {\n        int m = grid.Length, n = grid[0].Length;\n        for (int i = 0; i < m; i++) {\n            Array.Sort(grid[i]);\n        }\n        int res = 0;\n        for (int j = 0; j < n; j++) {\n            int mx = 0;\n            for (int i = 0; i < m; i++) {\n                mx = Math.Max(mx, grid[i][j]);\n            }\n            res += mx;\n        }\n        return res;\n    }\n}\n```\n\n```Go [sol1-Go]\nfunc deleteGreatestValue(grid [][]int) int {\n    m := len(grid)\n    n := len(grid[0])\n    for i := 0; i < m; i++ {\n        sort.Ints(grid[i])\n    }\n    res := 0\n    for j := 0; j < n; j++ {\n        mx := 0\n        for i := 0; i < m; i++ {\n            mx = max(mx, grid[i][j])\n        }\n        res += mx\n    }\n    return res\n}\n\nfunc max(a, b int) int {\n    if a > b {\n        return a\n    }\n    return b\n}\n```\n\n```JavaScript [sol1-JavaScript]\nvar deleteGreatestValue = function(grid) {\n    const m = grid.length, n = grid[0].length;\n    for (let i = 0; i < m; i++) {\n        grid[i].sort((a, b) => a - b);\n    }\n    let res = 0;\n    for (let j = 0; j < n; j++) {\n        let mx = 0;\n        for (let i = 0; i < m; i++) {\n            mx = Math.max(mx, grid[i][j]);\n        }\n        res += mx;\n    }\n    return res;\n};\n```\n\n```C [sol1-C]\nint cmp(void const* a, void const* b) {\n    return *(int*)a - *(int*)b;\n}\n\nint deleteGreatestValue(int** grid, int gridSize, int* gridColSize) {\n    int m = gridSize, n = *gridColSize;\n    for (int i = 0; i < m; ++i) {\n        qsort(grid[i], n, 4U, cmp);\n    }\n    int res = 0;\n    for (int j = 0; j < n; j++) {\n        int mx = 0;\n        for (int i = 0; i < m; ++i) {\n            if (grid[i][j] > mx) {\n                mx = grid[i][j];\n            }\n        }\n        res += mx;\n    }\n    return res;\n}\n```\n\n**复杂度分析**\n\n- 时间复杂度：$O(m \\times n \\times \\log n)$，其中 $m$，$n$ 分别为矩阵 $\\textit{grid}$ 的行列数，对矩阵 $\\textit{grid}$ 的每一行排序的时间复杂度为 $n \\times \\log n$，共有 $m$ 行，所以总的时间复杂度为 $O(m \\times n \\times \\log n)$。\n- 空间复杂度：$O(\\log n)$，排序需要的栈开销。",
            "slateValue": "",
            "slug": "shan-chu-mei-xing-zhong-de-zui-da-zhi-by-6fh9",
            "sunk": false,
            "chargeType": "FREE",
            "status": "PUBLISHED",
            "identifier": "pCQxEs",
            "canEdit": false,
            "canSee": true,
            "reactionType": null,
            "reactionsV2": [
                {
                    "count": 10,
                    "reactionType": "UPVOTE"
                }
            ],
            "tags": [
                {
                    "name": "Array",
                    "nameTranslated": "数组",
                    "slug": "array",
                    "tagType": "TOPIC"
                },
                {
                    "name": "Matrix",
                    "nameTranslated": "矩阵",
                    "slug": "matrix",
                    "tagType": "TOPIC"
                },
                {
                    "name": "C",
                    "nameTranslated": "",
                    "slug": "c",
                    "tagType": "LANGUAGE"
                },
                {
                    "name": "C++",
                    "nameTranslated": "",
                    "slug": "cpp",
                    "tagType": "LANGUAGE"
                },
                {
                    "name": "C#",
                    "nameTranslated": "",
                    "slug": "csharp",
                    "tagType": "LANGUAGE"
                },
                {
                    "name": "Go",
                    "nameTranslated": "",
                    "slug": "golang",
                    "tagType": "LANGUAGE"
                },
                {
                    "name": "Java",
                    "nameTranslated": "",
                    "slug": "java",
                    "tagType": "LANGUAGE"
                },
                {
                    "name": "JavaScript",
                    "nameTranslated": "",
                    "slug": "javascript",
                    "tagType": "LANGUAGE"
                },
                {
                    "name": "Python",
                    "nameTranslated": "",
                    "slug": "python",
                    "tagType": "LANGUAGE"
                }
            ],
            "createdAt": "2023-07-24T02:18:14.100687+00:00",
            "thumbnail": "",
            "author": {
                "username": "LeetCode-Solution",
                "certificationLevel": "OFFICIAL",
                "isDiscussAdmin": true,
                "isDiscussStaff": true,
                "profile": {
                    "userAvatar": "https://assets.leetcode.cn/aliyun-lc-upload/users/leetcode-solution/avatar_1582018938.png",
                    "userSlug": "leetcode-solution",
                    "realName": "力扣官方题解",
                    "reputation": 245
                }
            },
            "summary": "方法一：排序 思路与算法 我们将题目给出大小为 $m \\times n$ 的矩阵 $\\textit{grid}$ 每一行从小到大排序，那么题目等价于每次删除矩阵的末尾列，得分为该列的最大值。那么最后的答案就是每一列的最大值之和。 代码 Python [sol1-Python3] class Solution:     ",
            "topic": {
                "id": 2356397,
                "subscribed": false,
                "commentCount": 51,
                "viewCount": 879,
                "post": {
                    "id": 4429770,
                    "status": "Prepub",
                    "voteStatus": 0,
                    "isOwnPost": false
                }
            },
            "byLeetcode": true,
            "isMyFavorite": false,
            "isMostPopular": false,
            "favoriteCount": 19,
            "isEditorsPick": false,
            "hitCount": 9544,
            "videosInfo": [],
            "question": {
                "titleSlug": "delete-greatest-value-in-each-row",
                "questionFrontendId": "2500"
            },
            "next": {
                "slug": "wu-xu-mo-ni-pai-xu-ji-ke-by-endlesscheng-g2cd",
                "title": "无需模拟，排序即可（Python/Java/C++/Go/JS）"
            },
            "prev": null
        }
    }
}